devind_dictionaries/__init__.py
devind_dictionaries/apps.py
devind_dictionaries/fixtures/budget_classification.json
devind_dictionaries/migrations/0001_initial.py
devind_dictionaries/migrations/0002_auto_20220407_2148.py
devind_dictionaries/migrations/0003_auto_20220420_2056.py
devind_dictionaries/migrations/0004_auto_20220421_2151.py
devind_dictionaries/migrations/0005_alter_budgetclassification_updated_at.py
devind_dictionaries/migrations/__init__.py
devind_dictionaries/models/__init__.py
devind_dictionaries/models/budget_classification.py
devind_dictionaries/models/department.py
devind_dictionaries/models/districts.py
devind_dictionaries/models/organizations.py
devind_dictionaries/schema/__init__.py
devind_dictionaries/schema/filters.py
devind_dictionaries/schema/types.py
devind_dictionaries/services/__init__.py
devind_dictionaries/services/budget_classification_services.py
devind_dictionaries/services/organization_services.py
devind_dictionaries/settings.py
devind_dictionaries/tasks/__init__.py
devind_dictionaries/tasks/update_organizations.py
devind_dictionaries/tests/__init__.py
devind_dictionaries/tests/data/organizations.xml
devind_dictionaries/tests/test_budget_classification.py
devind_dictionaries/tests/test_queries.py
devind_dictionaries/tests/test_services.py
devind_dictionaries/tests/test_settings.py
devind_dictionaries-1.0.0.dist-info/LICENSE
devind_dictionaries-1.0.0.dist-info/WHEEL
devind_dictionaries-1.0.0.dist-info/METADATA
devind_dictionaries-1.0.0.dist-info/RECORD
